README.md
setup.py
deos.org.egg-info/PKG-INFO
deos.org.egg-info/SOURCES.txt
deos.org.egg-info/dependency_links.txt
deos.org.egg-info/not-zip-safe
deos.org.egg-info/top_level.txt
deos/org/__init__.py