Metadata-Version: 1.0
Name: deos.org
Version: 0.1
Summary: deos.org
Home-page: https://github.com/desantis/python-deos.org
Author: Andrew T. DeSantis
Author-email: atd@deos.org
License: MIT
Platform: UNKNOWN
